cryptdomainmgr/__init__.py
cryptdomainmgr/__main__.py
cryptdomainmgr/cdmconfighandler.py
cryptdomainmgr/cdmcore.py
cryptdomainmgr/cdmstatehandler.py
cryptdomainmgr/modules/__init__.py
cryptdomainmgr/modules/cdm/__init__.py
cryptdomainmgr/modules/cdm/confighandler.py
cryptdomainmgr/modules/cdm/main.py
cryptdomainmgr/modules/cert/__init__.py
cryptdomainmgr/modules/cert/confighandler.py
cryptdomainmgr/modules/cert/handlerdehydrated.py
cryptdomainmgr/modules/cert/hook.sh
cryptdomainmgr/modules/cert/main.py
cryptdomainmgr/modules/cert/dehydrated/.gitignore
cryptdomainmgr/modules/cert/dehydrated/CHANGELOG
cryptdomainmgr/modules/cert/dehydrated/LICENSE
cryptdomainmgr/modules/cert/dehydrated/README.md
cryptdomainmgr/modules/cert/dehydrated/dehydrated
cryptdomainmgr/modules/common/__init__.py
cryptdomainmgr/modules/common/cdmconfighelper.py
cryptdomainmgr/modules/common/cdmfilehelper.py
cryptdomainmgr/modules/common/cdmstatehelper.py
cryptdomainmgr/modules/common/main.py
cryptdomainmgr/modules/dhparam/__init__.py
cryptdomainmgr/modules/dhparam/confighandler.py
cryptdomainmgr/modules/dhparam/handleropenssl.py
cryptdomainmgr/modules/dhparam/main.py
cryptdomainmgr/modules/dkim/__init__.py
cryptdomainmgr/modules/dkim/confighandler.py
cryptdomainmgr/modules/dkim/dkim_signing_template.conf
cryptdomainmgr/modules/dkim/handlerrspamd.py
cryptdomainmgr/modules/dkim/main.py
cryptdomainmgr/modules/docker/__init__.py
cryptdomainmgr/modules/docker/dockerconfighelper.py
cryptdomainmgr/modules/domain/__init__.py
cryptdomainmgr/modules/domain/confighandler.py
cryptdomainmgr/modules/domain/handlerdnsuptools.py
cryptdomainmgr/modules/domain/main.py
cryptdomainmgr/modules/service/__init__.py
cryptdomainmgr/modules/service/confighandler.py
cryptdomainmgr/modules/service/handlerapache2.py
cryptdomainmgr/modules/service/handlerdovecot.py
cryptdomainmgr/modules/service/handlerpostfix.py
cryptdomainmgr/modules/service/handlerrspamd.py
cryptdomainmgr/modules/service/handlertraefik.py
cryptdomainmgr-0.2.4.post3.dist-info/LICENSE
cryptdomainmgr-0.2.4.post3.dist-info/METADATA
cryptdomainmgr-0.2.4.post3.dist-info/WHEEL
cryptdomainmgr-0.2.4.post3.dist-info/top_level.txt
cryptdomainmgr-0.2.4.post3.dist-info/RECORD
