Metadata-Version: 2.1
Name: cryptdomainmgr
Version: 0.2.4.post3
Summary: Software managing certificate, dkim and domain updates automagically.
Home-page: https://www.entroserv.de/offene-software/cryptdomainmgr
Author: Stefan Helmert
Author-email: stefan.helmert@t-online.de
License: https://www.fsf.org/licensing/licenses/agpl-3.0.html
Platform: UNKNOWN
Classifier: Programming Language :: Python :: 3
Classifier: License :: OSI Approved :: GNU Affero General Public License v3
Classifier: Operating System :: OS Independent
Requires-Dist: Jinja2
Requires-Dist: configparser
Requires-Dist: dnsuptools
Requires-Dist: parse
Requires-Dist: pyOpenSSL
Requires-Dist: simpleloggerplus
